cstation.py
docker/main.py
github/main.py
github/repo.py
server/main.py
cstation-0.1.21.dist-info/METADATA
cstation-0.1.21.dist-info/WHEEL
cstation-0.1.21.dist-info/entry_points.txt
cstation-0.1.21.dist-info/top_level.txt
cstation-0.1.21.dist-info/RECORD
