Metadata-Version: 2.1
Name: cstation
Version: 0.1.21
Summary: Managing PerfectWork Platform Infrastracture
Author: Loh W S (Wilson)
Requires-Python: >=3.9
Requires-Dist: auto-click-auto>=0.1.5
Requires-Dist: click>=8.1.7
